./.gitignore
./PKG-INFO
./README.md
./pyproject.toml
./server.py
excel2json_mcp_server-0.1.0.dist-info/METADATA
excel2json_mcp_server-0.1.0.dist-info/WHEEL
excel2json_mcp_server-0.1.0.dist-info/entry_points.txt
excel2json_mcp_server-0.1.0.dist-info/RECORD
