Metadata-Version: 2.4
Name: excel2json_mcp_server
Version: 0.1.0
Summary: MCP server for converting Excel files to JSON format with support for merged cells and Chinese characters
Project-URL: Homepage, https://github.com/v587d/excel2json-mcp-server
Project-URL: Repository, https://github.com/v587d/excel2json-mcp-server
Project-URL: Issues, https://github.com/v587d/excel2json-mcp-server/issues
Author-email: Shawn Hui <shawnhui1012@gmail.com>
License: MIT
Keywords: converter,excel,json,mcp,server
Classifier: Development Status :: 4 - Beta
Classifier: Intended Audience :: Developers
Classifier: License :: OSI Approved :: MIT License
Classifier: Programming Language :: Python :: 3
Classifier: Programming Language :: Python :: 3.9
Classifier: Programming Language :: Python :: 3.10
Classifier: Programming Language :: Python :: 3.11
Classifier: Programming Language :: Python :: 3.12
Requires-Python: >=3.12
Requires-Dist: mcp>=1.0.0
Requires-Dist: openpyxl>=3.1.0
Requires-Dist: pandas>=2.0.0
